nanophotonics/__init__.py
nanophotonics/example.py
nanophotonics-0.0.1.dist-info/METADATA
nanophotonics-0.0.1.dist-info/WHEEL
nanophotonics-0.0.1.dist-info/licenses/LICENSE
nanophotonics-0.0.1.dist-info/RECORD
